{
  "info": {
    "version": "0.0.1",
    "name": "thinkfrontend"
  },
  "resources": [
    {
      "id": 1,
      "url": "https://lmgtfy.com/q?=Flexbox",
      "title": "Read this article about CSS Flexbox"
    },
    {
      "id": 2,
      "url": "https://lmgtfy.com/q?=javascript.info",
      "title": "Read everything on this site explaining what is JS???"
    }
  ],
  "tasks": [
    {
      "id": "a85fd548-b4fc-4f60-83dc-5b84e6a2b0f0-a",
      "title": "HTML",
      "description": "Read about HTML",
      "main": [
        "a85fd548-b4fc-4f60-83dc-5b84e6a2b0f0"
      ],
      "optional": [
        "a85fd548-b4fc-4f60-83dc-5b84e6a2b0f0"
      ]
    },
    {
      "id": "a85fd548-b4fc-4f60-83dc-5b84e6a2b0f0-b",
      "title": "CSS",
      "description": "Read about CSS",
      "main": [
        "a85fd548-b4fc-4f60-83dc-5b84e6a2b0f0"
      ],
      "optional": [
        "a85fd548-b4fc-4f60-83dc-5b84e6a2b0f0"
      ]
    }
  ],
  "roadmaps": {
    "think-frontend": {
      "metrics": {
        "views" : 1,
        "likes" : 1,
        "shares": 1
      },
      "slug": "think-frontend",
      "title": "Think Frontend",
      "description": "Everything about frontend development. Get started with getting to know more about browsers, common tools and some terminology. Move on to the languages of the web and more."

    },
    "backend-101": {
      "metrics": {
        "views" : 2,
        "likes" : 4,
        "shares": 1
      },
      "title": "Backend 101",
      "slug": "backend-101",
      "description": "How data is saved, common backend design patterns, servers, and more."
    }
  },
  "users": [
    {
      "id": 1,
      "name": "Kim",
      "handle": "@kimskogsmo",
      "started": [
        {
          "roadmapId": 1,
          "completedTasks": []
        }
      ],
      "completed": []
    }
  ]
}